databento_dbn/__init__.py
databento_dbn/_lib.cpython-310-darwin.so
databento_dbn/_lib.pyi
databento_dbn/metadata.py
databento_dbn/py.typed
databento_dbn/v1.py
databento_dbn/v2.py
databento_dbn/v3.py
databento_dbn-0.46.0.dist-info/METADATA
databento_dbn-0.46.0.dist-info/WHEEL
databento_dbn-0.46.0.dist-info/RECORD
