Metadata-Version: 2.4
Name: databento-dbn
Version: 0.46.0
Classifier: Programming Language :: Rust
Classifier: Programming Language :: Python :: Implementation :: CPython
Summary: Python bindings for encoding and decoding Databento Binary Encoding (DBN)
Author-email: Databento <support@databento.com>
License-Expression: Apache-2.0
Requires-Python: >=3.10
Project-URL: Bug Tracker, https://github.com/databento/dbn/issues
Project-URL: Documentation, https://databento.com/docs
Project-URL: Homepage, https://databento.com
Project-URL: Repository, https://github.com/databento/dbn
